whereval/__init__.py
whereval/util.py
whereval/whereval.py
whereval-0.1.8.dist-info/LICENSE
whereval-0.1.8.dist-info/WHEEL
whereval-0.1.8.dist-info/METADATA
whereval-0.1.8.dist-info/RECORD
