Metadata-Version: 2.1
Name: whereval
Version: 0.1.8
Summary: Tool for parsing SQL like where expressions and evaluating against live data 
Home-page: https://pypi.org/project/whereval
License: MIT
Author: Timothy C. Quinn
Requires-Python: >=3.7.9,<4.0.0
Classifier: Development Status :: 4 - Beta
Classifier: Environment :: Console
Classifier: Intended Audience :: Developers
Classifier: License :: OSI Approved :: MIT License
Classifier: Operating System :: MacOS :: MacOS X
Classifier: Operating System :: POSIX :: BSD
Classifier: Operating System :: POSIX :: Linux
Classifier: Operating System :: POSIX :: SunOS/Solaris
Classifier: Programming Language :: Python :: 3
Classifier: Programming Language :: Python :: 3 :: Only
Classifier: Programming Language :: Python :: 3.10
Classifier: Programming Language :: Python :: 3.11
Classifier: Programming Language :: Python :: 3.7
Classifier: Programming Language :: Python :: 3.8
Classifier: Programming Language :: Python :: 3.9
Classifier: Topic :: Software Development
Requires-Dist: numpy (>=1.21.2,<2.0.0)
Requires-Dist: sqlparse (>=0.4.2,<0.5.0)
Requires-Dist: texttable (>=1.6.4,<2.0.0)
Project-URL: Repository, https://github.com/JavaScriptDude/WherEval
